pywebauthorization
