Metadata-Version: 2.1
Name: pywebauthorization
Version: 0.0.2
Author: Loren Hayden
Author-email: lorenhayden@hotmail.com
